__init__.py
nix/__init__.py
nix/classes/__init__.py
nix/classes/_io.py
nix/decorators/__init__.py
nix/decorators/_handle_exception.py
nix/decorators/_retry.py
nix/decorators/_thread_pool.py
nix_python_utils-0.1.0.dist-info/LICENSE
nix_python_utils-0.1.0.dist-info/METADATA
nix_python_utils-0.1.0.dist-info/WHEEL
nix_python_utils-0.1.0.dist-info/top_level.txt
nix_python_utils-0.1.0.dist-info/RECORD
