Metadata-Version: 2.1
Name: nix-python-utils
Version: 0.1.0
Summary: Useful Python decorators that I use in development.
Author-email: Nix ツ <nikusunix@gmail.com>
Maintainer-email: Nix ツ <nikusunix@gmail.com>
License: MIT License
Project-URL: Homepage, https://github.com/nixnks/nix-python-utils
Project-URL: Documentation, https://github.com/nixnks/nix-python-utils
Project-URL: Repository, https://github.com/nixnks/nix-python-utils
Project-URL: Changelog, https://github.com/nixnks/nix-python-utils/CHANGELOG.md
Keywords: python,utils,useful,library
Classifier: Programming Language :: Python
Requires-Python: >=3.11
License-File: LICENSE
